plugin.cmake
pyproject.toml
setup.py
girder_dicom_viewer/__init__.py
girder_dicom_viewer/event_helper.py
girder_dicom_viewer.egg-info/PKG-INFO
girder_dicom_viewer.egg-info/SOURCES.txt
girder_dicom_viewer.egg-info/dependency_links.txt
girder_dicom_viewer.egg-info/entry_points.txt
girder_dicom_viewer.egg-info/not-zip-safe
girder_dicom_viewer.egg-info/requires.txt
girder_dicom_viewer.egg-info/top_level.txt
girder_dicom_viewer/web_client/main.js
girder_dicom_viewer/web_client/package.json
girder_dicom_viewer/web_client/webpack.helper.js
girder_dicom_viewer/web_client/stylesheets/dicomItem.styl
girder_dicom_viewer/web_client/stylesheets/dicomSliceMetadata.styl
girder_dicom_viewer/web_client/templates/dicomItem.pug
girder_dicom_viewer/web_client/templates/dicomSliceMetadata.pug
girder_dicom_viewer/web_client/templates/parseDicomItem.pug
girder_dicom_viewer/web_client/views/DicomView.js
plugin_tests/__init__.py
plugin_tests/dicom_viewer_test.py
plugin_tests/data/000000.dcm.sha512
plugin_tests/data/000001.dcm.sha512
plugin_tests/data/000002.dcm.sha512
plugin_tests/data/000003.dcm.sha512