Metadata-Version: 2.4
Name: girder-dicom-viewer
Version: 3.2.12.dev2
Summary: View DICOM images in the browser
Home-page: http://girder.readthedocs.io/en/latest/plugins.html#dicom-viewer
Author: Kitware, Inc.
Author-email: kitware@kitware.com
License: Apache 2.0
Classifier: Development Status :: 4 - Beta
Classifier: Environment :: Web Environment
Classifier: Operating System :: OS Independent
Classifier: Programming Language :: Python
Classifier: Programming Language :: Python :: 3
Requires-Python: >=3.8
Requires-Dist: girder>=3
Requires-Dist: pydicom>=2
Dynamic: author
Dynamic: author-email
Dynamic: classifier
Dynamic: home-page
Dynamic: license
Dynamic: requires-dist
Dynamic: requires-python
Dynamic: summary
